zenofelon.py
zenofelon-0.0.1.dist-info/METADATA
zenofelon-0.0.1.dist-info/WHEEL
zenofelon-0.0.1.dist-info/top_level.txt
zenofelon-0.0.1.dist-info/RECORD
