Metadata-Version: 2.1
Name: zenofelon
Version: 0.0.1
Summary: Zen of Elon
Author-email: Bert Lievrouw <b@bertlievrouw.com>
